odoo/addons/mail_history/README.rst
odoo/addons/mail_history/__init__.py
odoo/addons/mail_history/__manifest__.py
odoo/addons/mail_history/hooks.py
odoo/addons/mail_history/i18n/da.po
odoo/addons/mail_history/i18n/fr.po
odoo/addons/mail_history/i18n/mail_history.pot
odoo/addons/mail_history/models/__init__.py
odoo/addons/mail_history/models/mail_message.py
odoo/addons/mail_history/models/mail_notification.py
odoo/addons/mail_history/readme/CONFIGURE.rst
odoo/addons/mail_history/readme/CONTRIBUTORS.rst
odoo/addons/mail_history/readme/DESCRIPTION.rst
odoo/addons/mail_history/readme/INSTALL.rst
odoo/addons/mail_history/readme/ROADMAP.rst
odoo/addons/mail_history/readme/USAGE.rst
odoo/addons/mail_history/static/description/icon.png
odoo/addons/mail_history/static/description/index.html
odoo/addons/mail_history/static/src/js/discuss.js
odoo/addons/mail_history/static/src/js/mail_manager.js
odoo/addons/mail_history/static/src/js/mailbox.js
odoo/addons/mail_history/static/src/js/message.js
odoo/addons/mail_history/static/src/xml/discuss.xml
odoo/addons/mail_history/static/src/xml/thread.xml
odoo/addons/mail_history/views/assets.xml
odoo12_addon_mail_history-12.0.1.0.0.99.dev10.dist-info/METADATA
odoo12_addon_mail_history-12.0.1.0.0.99.dev10.dist-info/WHEEL
odoo12_addon_mail_history-12.0.1.0.0.99.dev10.dist-info/top_level.txt
odoo12_addon_mail_history-12.0.1.0.0.99.dev10.dist-info/RECORD
